MANIFEST.in
README
VERSION
setup.py
generaltools/__init__.py
generaltools/database_tools.py
generaltools/date_tools.py
generaltools/file_tools.py
generaltools/log_tools.py
generaltools/server_tools.py
generaltools/system_tools.py
generaltools.egg-info/PKG-INFO
generaltools.egg-info/SOURCES.txt
generaltools.egg-info/dependency_links.txt
generaltools.egg-info/not-zip-safe
generaltools.egg-info/requires.txt
generaltools.egg-info/top_level.txt