Metadata-Version: 1.0
Name: generaltools
Version: 0.0.16
Summary: Collection of function snippets often used in our python environment
Home-page: https://github.com/buchbend/generaltools.git
Author: Christof Buchbender
Author-email: buchbend@ph1.uni-koeln.de
License: MIT
Platform: UNKNOWN
